{
  "date": "2026-06-16",
  "generatedAt": "2026-06-16T10:01:34.493Z",
  "source": "https://fussballgucken.info/fussball-heute",
  "languages": [
    "de",
    "tr",
    "en"
  ],
  "summary": {
    "de": "8 Übertragungen heute, u.a. Saudi Arabien - Uruguay (00:00 Uhr).",
    "tr": "Bugün 8 yayın, Saudi Arabien - Uruguay dahil (00:00).",
    "en": "8 broadcasts today, including Saudi Arabien - Uruguay (00:00)."
  },
  "matches": [
    {
      "time": "00:00",
      "competition": "WM 2026",
      "stage": {
        "de": "Gruppenphase Gruppe H",
        "tr": "Grupnphase Grup H",
        "en": "Groupnphase Group H"
      },
      "homeTeam": "Saudi Arabien",
      "awayTeam": "Uruguay",
      "channels": [
        "FUSSBALL.TV 1 (MagentaTV)",
        "MagentaTV",
        "ZDF",
        "ServusTV (AT)",
        "M6"
      ],
      "isHighlight": false,
      "kickoff": "2026-06-16T00:00:00+02:00"
    },
    {
      "time": "03:00",
      "competition": "WM 2026",
      "stage": {
        "de": "Gruppenphase Gruppe G",
        "tr": "Grupnphase Grup G",
        "en": "Groupnphase Group G"
      },
      "homeTeam": "Iran",
      "awayTeam": "Neuseeland",
      "channels": [
        "FUSSBALL.TV 1 (MagentaTV)",
        "MagentaTV",
        "ZDF",
        "ServusTV (AT)",
        "RSI LA 2"
      ],
      "isHighlight": false,
      "kickoff": "2026-06-16T03:00:00+02:00"
    },
    {
      "time": "17:00",
      "competition": "Virsliga (Lettland)",
      "stage": {
        "de": "18. Spieltag",
        "tr": "18. Hafta",
        "en": "Matchday 18"
      },
      "homeTeam": "BFC Daugavpils",
      "awayTeam": "SK Super Nova",
      "channels": [
        "OneFootball",
        "OneFootball (App)",
        "OneFootball TV (Amazon FireTV)",
        "OneFootball TV (Android/Google TV)",
        "OneFootball TV (Apple TV)"
      ],
      "isHighlight": false,
      "kickoff": "2026-06-16T17:00:00+02:00"
    },
    {
      "time": "18:00",
      "competition": "Virsliga (Lettland)",
      "stage": {
        "de": "18. Spieltag",
        "tr": "18. Hafta",
        "en": "Matchday 18"
      },
      "homeTeam": "Grobinas Sporta Centrs",
      "awayTeam": "FK Liepaja",
      "channels": [
        "OneFootball",
        "OneFootball (App)",
        "OneFootball TV (Amazon FireTV)",
        "OneFootball TV (Android/Google TV)",
        "OneFootball TV (Apple TV)"
      ],
      "isHighlight": false,
      "kickoff": "2026-06-16T18:00:00+02:00"
    },
    {
      "time": "21:00",
      "competition": "WM 2026",
      "stage": {
        "de": "Gruppenphase Gruppe I",
        "tr": "Grupnphase Grup I",
        "en": "Groupnphase Group I"
      },
      "homeTeam": "Frankreich",
      "awayTeam": "Senegal",
      "channels": [
        "FUSSBALL.TV 1 (MagentaTV)",
        "MagentaTV",
        "ORF 1",
        "Rai 1",
        "M6"
      ],
      "isHighlight": false,
      "kickoff": "2026-06-16T21:00:00+02:00"
    },
    {
      "time": "21:15",
      "competition": "Besta deild karla (Island)",
      "stage": {
        "de": "10. Spieltag",
        "tr": "10. Hafta",
        "en": "Matchday 10"
      },
      "homeTeam": "Vikingur Reykjavik",
      "awayTeam": "KR Reykjavik",
      "channels": [
        "OneFootball",
        "OneFootball (App)",
        "OneFootball TV (Amazon FireTV)",
        "OneFootball TV (Android/Google TV)",
        "OneFootball TV (Apple TV)"
      ],
      "isHighlight": false,
      "kickoff": "2026-06-16T21:15:00+02:00"
    },
    {
      "time": "21:15",
      "competition": "Besta deild karla (Island)",
      "stage": {
        "de": "10. Spieltag",
        "tr": "10. Hafta",
        "en": "Matchday 10"
      },
      "homeTeam": "IA Akranes",
      "awayTeam": "Valur Reykjavik",
      "channels": [
        "OneFootball",
        "OneFootball (App)",
        "OneFootball TV (Amazon FireTV)",
        "OneFootball TV (Android/Google TV)",
        "OneFootball TV (Apple TV)"
      ],
      "isHighlight": false,
      "kickoff": "2026-06-16T21:15:00+02:00"
    },
    {
      "time": "21:15",
      "competition": "Besta deild karla (Island)",
      "stage": {
        "de": "10. Spieltag",
        "tr": "10. Hafta",
        "en": "Matchday 10"
      },
      "homeTeam": "UMF Stjarnan",
      "awayTeam": "Breidablik Kópavogur",
      "channels": [
        "OneFootball",
        "OneFootball (App)",
        "OneFootball TV (Amazon FireTV)",
        "OneFootball TV (Android/Google TV)",
        "OneFootball TV (Apple TV)"
      ],
      "isHighlight": false,
      "kickoff": "2026-06-16T21:15:00+02:00"
    }
  ]
}